{
  "generatedAt": "2026-06-18T16:16:13.195Z",
  "story": {
    "title": "Actualizaciones en Vivo de la Guerra con Irán: Vance Defiende el Acuerdo con Irán mientras Crece la Crítica",
    "link": "https://www.nytimes.com/live/2026/06/18/world/iran-war-trump-us-deal",
    "pubDate": "2026-06-18T16:13:15.000Z",
    "snippet": "El vicepresidente dijo a los reporteros que el programa nuclear de Irán 'ha sido completamente destruido' y su capacidad de amenazar a sus vecinos está 'prácticamente desaparecida'. Sostuvo que Irán solo recibirá beneficios económicos si sus líderes 'cambian su comportamiento'.",
    "source": "The New York Times"
  }
}
